jupyterlabutils/__init__.py
jupyterlabutils/_version.py
jupyterlabutils/notebook/__init__.py
jupyterlabutils/notebook/catalog.py
jupyterlabutils/notebook/forwarder.py
jupyterlabutils/notebook/utils.py
jupyterlabutils/rubinlabapp/__init__.py
jupyterlabutils/rubinlabapp/labhubapp.py
jupyterlabutils/rubinlabapp/rubinlabapp.py
jupyterlabutils-0.10.0.dist-info/LICENSE
jupyterlabutils-0.10.0.dist-info/METADATA
jupyterlabutils-0.10.0.dist-info/WHEEL
jupyterlabutils-0.10.0.dist-info/entry_points.txt
jupyterlabutils-0.10.0.dist-info/top_level.txt
jupyterlabutils-0.10.0.dist-info/RECORD
